green_mbtools-0.3.0.dist-info/RECORD
green_mbtools-0.3.0.dist-info/WHEEL
green_mbtools-0.3.0.dist-info/top_level.txt
green_mbtools-0.3.0.dist-info/METADATA
green_mbtools-0.3.0.dist-info/licenses/LICENSE
mbanalysis/__init__.py
green_mbtools/__init__.py
green_mbtools/mint/seet_init.py
green_mbtools/mint/__init__.py
green_mbtools/mint/ortho_utils.py
green_mbtools/mint/integral_utils.py
green_mbtools/mint/gdf_s_metric.py
green_mbtools/mint/namespace.py
green_mbtools/mint/common_utils.py
green_mbtools/mint/pyscf_init.py
green_mbtools/pesto/dyson.py
green_mbtools/pesto/ac_utils.py
green_mbtools/pesto/caratheodory.cpython-310-darwin.so
green_mbtools/pesto/pes_utils.py
green_mbtools/pesto/ft.py
green_mbtools/pesto/__init__.py
green_mbtools/pesto/cheby.py
green_mbtools/pesto/winter.py
green_mbtools/pesto/ir.py
green_mbtools/pesto/orth.py
green_mbtools/pesto/quasiparticle.py
green_mbtools/pesto/analyt_cont.py
green_mbtools/pesto/spectral.py
green_mbtools/pesto/mb.py
green_mbtools/.dylibs/libgmpxx.4.dylib
green_mbtools/.dylibs/libgmp.10.dylib
green_mbtools/.dylibs/libmpfr.6.dylib
