Metadata-Version: 2.1
Name: green-mbtools
Version: 0.3.0
Summary: Collection of Python tools for quantum many-body simulation using Green Software Package
Author-email: Chia-Nan Yeh <cyeh@flatironinstitute.org>, Gaurav Harsha <gharsha@umich.edu>, Sergei Iskakov <siskakov@umich.edu>, Vibin Abraham <avibin@umich.edu>, Pavel Pokhilko <pokhilko@umich.edu>
Maintainer-email: Sergei Iskakov <siskakov@umich.edu>, Gaurav Harsha <gharsha@umich.edu>, Vibin Abraham <avibin@umich.edu>, Pavel Pokhilko <pokhilko@umich.edu>
Project-URL: Homepage, https://green-phys.org
Project-URL: Issues, https://github.com/Green-Phys/green-mbtools/issues
Classifier: Development Status :: 4 - Beta
Classifier: Programming Language :: Python :: 3
Classifier: License :: OSI Approved :: MIT License
Classifier: Operating System :: POSIX
Classifier: Operating System :: Unix
Classifier: Operating System :: MacOS
Requires-Python: <3.13,>=3.8
License-File: LICENSE
Requires-Dist: numpy
Requires-Dist: ase
Requires-Dist: spglib
Requires-Dist: numba
Requires-Dist: pyscf
Requires-Dist: scipy
Requires-Dist: h5py
Requires-Dist: green-ac
Requires-Dist: green-igen
Requires-Dist: irbasis
Requires-Dist: baryrat
Requires-Dist: cvxpy
Requires-Dist: clarabel
Requires-Dist: mosek
Provides-Extra: tests
Requires-Dist: coverage>=5.0.3; extra == "tests"
Requires-Dist: pytest; extra == "tests"
Requires-Dist: pytest-benchmark[histogram]>=3.2.1; extra == "tests"
